urdf_mesh_inertia/__init__.py
urdf_mesh_inertia/__main__.py
urdf_mesh_inertia/mesh.py
urdf_mesh_inertia/xml.py
urdf_mesh_inertia-0.2.0.dist-info/LICENSE
urdf_mesh_inertia-0.2.0.dist-info/METADATA
urdf_mesh_inertia-0.2.0.dist-info/WHEEL
urdf_mesh_inertia-0.2.0.dist-info/entry_points.txt
urdf_mesh_inertia-0.2.0.dist-info/RECORD
