Metadata-Version: 2.1
Name: urdf-mesh-inertia
Version: 0.2.0
Summary: Compute inertial parameters for a mesh using pymeshlab and return the URDF inertial tag for links.
Home-page: https://github.com/eriol/urdf-mesh-inertia
License: BSD-3-Clause
Author: Daniele Tricoli
Author-email: eriol@mornie.org
Requires-Python: >=3.11,<4.0
Classifier: Development Status :: 4 - Beta
Classifier: Environment :: Console
Classifier: License :: OSI Approved :: BSD License
Classifier: Programming Language :: Python :: 3
Classifier: Programming Language :: Python :: 3.11
Classifier: Programming Language :: Python :: 3.12
Requires-Dist: jinja2 (>=3.1.4,<4.0.0)
Requires-Dist: pymeshlab (>=2023.12.post1,<2024.0)
Requires-Dist: typer (>=0.12.3,<0.13.0)
Project-URL: Repository, https://github.com/eriol/urdf-mesh-inertia
